allmaker.py
allmaker-0.1.2.dist-info/METADATA
allmaker-0.1.2.dist-info/WHEEL
allmaker-0.1.2.dist-info/top_level.txt
allmaker-0.1.2.dist-info/RECORD
